{
  "generated_at": "2026-06-24T19:59:28.402220+00:00",
  "source": "888sport",
  "bookmaker": "888Sport",
  "url": "https://www.888sport.com/ufc-mma/",
  "count": 4,
  "fights": [
    {
      "bookmaker": "888Sport",
      "fight": "Tahir Abdullayev vs Jefferson Nascimento",
      "fight_name": "Tahir Abdullayev vs Jefferson Nascimento",
      "url": "https://www.888sport.com/ufc-mma/",
      "markets": {
        "fight_betting": [
          {
            "selection": "Tahir Abdullayev",
            "odds": "4/5"
          },
          {
            "selection": "Jefferson Nascimento",
            "odds": "1/1"
          }
        ]
      },
      "raw_fight_name": "Tahir Abdullayev vs Jefferson Nascimento"
    },
    {
      "bookmaker": "888Sport",
      "fight": "Daniil Donchenko vs Theodor Berggren",
      "fight_name": "Daniil Donchenko vs Theodor Berggren",
      "url": "https://www.888sport.com/ufc-mma/",
      "markets": {
        "fight_betting": [
          {
            "selection": "Daniil Donchenko",
            "odds": "1/5"
          },
          {
            "selection": "Theodor Berggren",
            "odds": "7/2"
          }
        ]
      },
      "raw_fight_name": "Daniil Donchenko vs Theodor Berggren"
    },
    {
      "bookmaker": "888Sport",
      "fight": "Shara Magomedov vs Michel Pereira",
      "fight_name": "Shara Magomedov vs Michel Pereira",
      "url": "https://www.888sport.com/ufc-mma/",
      "markets": {
        "fight_betting": [
          {
            "selection": "Shara Magomedov",
            "odds": "4/15"
          },
          {
            "selection": "Michel Pereira",
            "odds": "14/5"
          }
        ]
      },
      "raw_fight_name": "Shara Magomedov vs M Pereira"
    },
    {
      "bookmaker": "888Sport",
      "fight": "L Carmouche vs V Araujo",
      "fight_name": "L Carmouche vs V Araujo",
      "url": "https://www.888sport.com/ufc-mma/",
      "markets": {
        "fight_betting": [
          {
            "selection": "L Carmouche",
            "odds": "1/3"
          },
          {
            "selection": "V Araujo",
            "odds": "2/1"
          }
        ]
      },
      "raw_fight_name": "L Carmouche vs V Araujo"
    }
  ]
}